{
    "recent": [
        {
            "rank": "1",
            "title": "Dive",
            "artist": "ziproom",
            "playcount": 12,
            "image": "https://lastfm.freetls.fastly.net/i/u/300x300/2a96cbd8b46e442fc41c2b86b821562f.png",
            "link": "https://www.last.fm/music/ziproom/_/Dive"
        },
        {
            "rank": "2",
            "title": "Electronica",
            "artist": "ziproom",
            "playcount": 9,
            "image": "https://lastfm.freetls.fastly.net/i/u/300x300/2a96cbd8b46e442fc41c2b86b821562f.png",
            "link": "https://www.last.fm/music/ziproom/_/Electronica"
        },
        {
            "rank": "3",
            "title": "Dance With Me",
            "artist": "ziproom",
            "playcount": 7,
            "image": "https://lastfm.freetls.fastly.net/i/u/300x300/2a96cbd8b46e442fc41c2b86b821562f.png",
            "link": "https://www.last.fm/music/ziproom/_/Dance+With+Me"
        },
        {
            "rank": "4",
            "title": "Get a million",
            "artist": "ziproom",
            "playcount": 7,
            "image": "https://lastfm.freetls.fastly.net/i/u/300x300/2a96cbd8b46e442fc41c2b86b821562f.png",
            "link": "https://www.last.fm/music/ziproom/_/Get+a+million"
        },
        {
            "rank": "5",
            "title": "MINT",
            "artist": "ziproom",
            "playcount": 7,
            "image": "https://lastfm.freetls.fastly.net/i/u/300x300/2a96cbd8b46e442fc41c2b86b821562f.png",
            "link": "https://www.last.fm/music/ziproom/_/MINT"
        },
        {
            "rank": "6",
            "title": "Katsushika",
            "artist": "ziproom",
            "playcount": 6,
            "image": "https://lastfm.freetls.fastly.net/i/u/300x300/2a96cbd8b46e442fc41c2b86b821562f.png",
            "link": "https://www.last.fm/music/ziproom/_/Katsushika"
        },
        {
            "rank": "7",
            "title": "DIE TRYING",
            "artist": "PARTYNEXTDOOR",
            "playcount": 5,
            "image": "https://lastfm.freetls.fastly.net/i/u/300x300/2a96cbd8b46e442fc41c2b86b821562f.png",
            "link": "https://www.last.fm/music/PARTYNEXTDOOR/_/DIE+TRYING"
        },
        {
            "rank": "8",
            "title": "ROUTINE",
            "artist": "ziproom",
            "playcount": 5,
            "image": "https://lastfm.freetls.fastly.net/i/u/300x300/2a96cbd8b46e442fc41c2b86b821562f.png",
            "link": "https://www.last.fm/music/ziproom/_/ROUTINE"
        },
        {
            "rank": "9",
            "title": "Mile",
            "artist": "ziproom",
            "playcount": 4,
            "image": "https://lastfm.freetls.fastly.net/i/u/300x300/2a96cbd8b46e442fc41c2b86b821562f.png",
            "link": "https://www.last.fm/music/ziproom/_/Mile"
        },
        {
            "rank": "10",
            "title": "42",
            "artist": "Coldplay",
            "playcount": 3,
            "image": "https://lastfm.freetls.fastly.net/i/u/300x300/2a96cbd8b46e442fc41c2b86b821562f.png",
            "link": "https://www.last.fm/music/Coldplay/_/42"
        },
        {
            "rank": "11",
            "title": "Viva la Vida",
            "artist": "Coldplay",
            "playcount": 3,
            "image": "https://lastfm.freetls.fastly.net/i/u/300x300/2a96cbd8b46e442fc41c2b86b821562f.png",
            "link": "https://www.last.fm/music/Coldplay/_/Viva+la+Vida"
        },
        {
            "rank": "12",
            "title": "Janice STFU",
            "artist": "Drake",
            "playcount": 3,
            "image": "https://lastfm.freetls.fastly.net/i/u/300x300/2a96cbd8b46e442fc41c2b86b821562f.png",
            "link": "https://www.last.fm/music/Drake/_/Janice+STFU"
        },
        {
            "rank": "13",
            "title": "One Dance",
            "artist": "Drake",
            "playcount": 3,
            "image": "https://lastfm.freetls.fastly.net/i/u/300x300/2a96cbd8b46e442fc41c2b86b821562f.png",
            "link": "https://www.last.fm/music/Drake/_/One+Dance"
        },
        {
            "rank": "14",
            "title": "Push Ups",
            "artist": "Drake",
            "playcount": 3,
            "image": "https://lastfm.freetls.fastly.net/i/u/300x300/2a96cbd8b46e442fc41c2b86b821562f.png",
            "link": "https://www.last.fm/music/Drake/_/Push+Ups"
        },
        {
            "rank": "15",
            "title": "Shabang",
            "artist": "Drake",
            "playcount": 3,
            "image": "https://lastfm.freetls.fastly.net/i/u/300x300/2a96cbd8b46e442fc41c2b86b821562f.png",
            "link": "https://www.last.fm/music/Drake/_/Shabang"
        },
        {
            "rank": "16",
            "title": "パズル",
            "artist": "Lilas",
            "playcount": 3,
            "image": "https://lastfm.freetls.fastly.net/i/u/300x300/2a96cbd8b46e442fc41c2b86b821562f.png",
            "link": "https://www.last.fm/music/Lilas/_/%E3%83%91%E3%82%BA%E3%83%AB"
        },
        {
            "rank": "17",
            "title": "ДОМ (Лондон, Прага, Ницца)",
            "artist": "Morgenshtern",
            "playcount": 3,
            "image": "https://lastfm.freetls.fastly.net/i/u/300x300/2a96cbd8b46e442fc41c2b86b821562f.png",
            "link": "https://www.last.fm/music/Morgenshtern/_/%D0%94%D0%9E%D0%9C+(%D0%9B%D0%BE%D0%BD%D0%B4%D0%BE%D0%BD,+%D0%9F%D1%80%D0%B0%D0%B3%D0%B0,+%D0%9D%D0%B8%D1%86%D1%86%D0%B0)"
        },
        {
            "rank": "18",
            "title": "Dat $tick",
            "artist": "Rich Brian",
            "playcount": 3,
            "image": "https://lastfm.freetls.fastly.net/i/u/300x300/2a96cbd8b46e442fc41c2b86b821562f.png",
            "link": "https://www.last.fm/music/Rich+Brian/_/Dat+$tick"
        },
        {
            "rank": "19",
            "title": "CARNIVAL",
            "artist": "¥$",
            "playcount": 2,
            "image": "https://lastfm.freetls.fastly.net/i/u/300x300/2a96cbd8b46e442fc41c2b86b821562f.png",
            "link": "https://www.last.fm/music/%C2%A5$/_/CARNIVAL"
        },
        {
            "rank": "20",
            "title": "The Days - NOTION Remix",
            "artist": "Chrystal",
            "playcount": 2,
            "image": "https://lastfm.freetls.fastly.net/i/u/300x300/2a96cbd8b46e442fc41c2b86b821562f.png",
            "link": "https://www.last.fm/music/Chrystal/_/The+Days+-+NOTION+Remix"
        },
        {
            "rank": "21",
            "title": "What Did I Miss?",
            "artist": "Drake",
            "playcount": 2,
            "image": "https://lastfm.freetls.fastly.net/i/u/300x300/2a96cbd8b46e442fc41c2b86b821562f.png",
            "link": "https://www.last.fm/music/Drake/_/What+Did+I+Miss%3F"
        },
        {
            "rank": "22",
            "title": "МОЙ КАЛАШНИКОВ",
            "artist": "Face",
            "playcount": 2,
            "image": "https://lastfm.freetls.fastly.net/i/u/300x300/2a96cbd8b46e442fc41c2b86b821562f.png",
            "link": "https://www.last.fm/music/Face/_/%D0%9C%D0%9E%D0%99+%D0%9A%D0%90%D0%9B%D0%90%D0%A8%D0%9D%D0%98%D0%9A%D0%9E%D0%92"
        },
        {
            "rank": "23",
            "title": "Let Me Hear",
            "artist": "Fear, and Loathing in Las Vegas",
            "playcount": 2,
            "image": "https://lastfm.freetls.fastly.net/i/u/300x300/2a96cbd8b46e442fc41c2b86b821562f.png",
            "link": "https://www.last.fm/music/Fear,+and+Loathing+in+Las+Vegas/_/Let+Me+Hear"
        },
        {
            "rank": "24",
            "title": "Somebody That I Used to Know",
            "artist": "Gotye",
            "playcount": 2,
            "image": "https://lastfm.freetls.fastly.net/i/u/300x300/2a96cbd8b46e442fc41c2b86b821562f.png",
            "link": "https://www.last.fm/music/Gotye/_/Somebody+That+I+Used+to+Know"
        },
        {
            "rank": "25",
            "title": "ホタルノヒカリ",
            "artist": "Ikimonogakari",
            "playcount": 2,
            "image": "https://lastfm.freetls.fastly.net/i/u/300x300/2a96cbd8b46e442fc41c2b86b821562f.png",
            "link": "https://www.last.fm/music/+noredirect/Ikimonogakari/_/%E3%83%9B%E3%82%BF%E3%83%AB%E3%83%8E%E3%83%92%E3%82%AB%E3%83%AA"
        },
        {
            "rank": "26",
            "title": "熱情のスペクトラム",
            "artist": "Ikimonogakari",
            "playcount": 2,
            "image": "https://lastfm.freetls.fastly.net/i/u/300x300/2a96cbd8b46e442fc41c2b86b821562f.png",
            "link": "https://www.last.fm/music/+noredirect/Ikimonogakari/_/%E7%86%B1%E6%83%85%E3%81%AE%E3%82%B9%E3%83%9A%E3%82%AF%E3%83%88%E3%83%A9%E3%83%A0"
        },
        {
            "rank": "27",
            "title": "Count Me Out",
            "artist": "Kendrick Lamar",
            "playcount": 2,
            "image": "https://lastfm.freetls.fastly.net/i/u/300x300/2a96cbd8b46e442fc41c2b86b821562f.png",
            "link": "https://www.last.fm/music/Kendrick+Lamar/_/Count+Me+Out"
        },
        {
            "rank": "28",
            "title": "DNA.",
            "artist": "Kendrick Lamar",
            "playcount": 2,
            "image": "https://lastfm.freetls.fastly.net/i/u/300x300/2a96cbd8b46e442fc41c2b86b821562f.png",
            "link": "https://www.last.fm/music/Kendrick+Lamar/_/DNA."
        },
        {
            "rank": "29",
            "title": "DUCKWORTH.",
            "artist": "Kendrick Lamar",
            "playcount": 2,
            "image": "https://lastfm.freetls.fastly.net/i/u/300x300/2a96cbd8b46e442fc41c2b86b821562f.png",
            "link": "https://www.last.fm/music/Kendrick+Lamar/_/DUCKWORTH."
        },
        {
            "rank": "30",
            "title": "20 Min",
            "artist": "Lil Uzi Vert",
            "playcount": 2,
            "image": "https://lastfm.freetls.fastly.net/i/u/300x300/2a96cbd8b46e442fc41c2b86b821562f.png",
            "link": "https://www.last.fm/music/Lil+Uzi+Vert/_/20+Min"
        },
        {
            "rank": "31",
            "title": "Shinzo wo Sasageyo !",
            "artist": "Linked Horizon",
            "playcount": 2,
            "image": "https://lastfm.freetls.fastly.net/i/u/300x300/2a96cbd8b46e442fc41c2b86b821562f.png",
            "link": "https://www.last.fm/music/Linked+Horizon/_/Shinzo+wo+Sasageyo+!"
        },
        {
            "rank": "32",
            "title": "“Tomodachi Game” Main Theme",
            "artist": "Michiru",
            "playcount": 2,
            "image": "https://lastfm.freetls.fastly.net/i/u/300x300/2a96cbd8b46e442fc41c2b86b821562f.png",
            "link": "https://www.last.fm/music/Michiru/_/%E2%80%9CTomodachi+Game%E2%80%9D+Main+Theme"
        },
        {
            "rank": "33",
            "title": "Swag",
            "artist": "miyauchi",
            "playcount": 2,
            "image": "https://lastfm.freetls.fastly.net/i/u/300x300/2a96cbd8b46e442fc41c2b86b821562f.png",
            "link": "https://www.last.fm/music/miyauchi/_/Swag"
        },
        {
            "rank": "34",
            "title": "ПУСТОЙ ВОКЗАЛ",
            "artist": "Morgenshtern",
            "playcount": 2,
            "image": "https://lastfm.freetls.fastly.net/i/u/300x300/2a96cbd8b46e442fc41c2b86b821562f.png",
            "link": "https://www.last.fm/music/Morgenshtern/_/%D0%9F%D0%A3%D0%A1%D0%A2%D0%9E%D0%99+%D0%92%D0%9E%D0%9A%D0%97%D0%90%D0%9B"
        },
        {
            "rank": "35",
            "title": "Alien Boy",
            "artist": "Oliver Tree",
            "playcount": 2,
            "image": "https://lastfm.freetls.fastly.net/i/u/300x300/2a96cbd8b46e442fc41c2b86b821562f.png",
            "link": "https://www.last.fm/music/Oliver+Tree/_/Alien+Boy"
        },
        {
            "rank": "36",
            "title": "Hurt",
            "artist": "Oliver Tree",
            "playcount": 2,
            "image": "https://lastfm.freetls.fastly.net/i/u/300x300/2a96cbd8b46e442fc41c2b86b821562f.png",
            "link": "https://www.last.fm/music/Oliver+Tree/_/Hurt"
        },
        {
            "rank": "37",
            "title": "Beinem Oiyńda",
            "artist": "rusha",
            "playcount": 2,
            "image": "https://lastfm.freetls.fastly.net/i/u/300x300/2a96cbd8b46e442fc41c2b86b821562f.png",
            "link": "https://www.last.fm/music/rusha/_/Beinem+Oiy%C5%84da"
        },
        {
            "rank": "38",
            "title": "kim?",
            "artist": "rusha",
            "playcount": 2,
            "image": "https://lastfm.freetls.fastly.net/i/u/300x300/2a96cbd8b46e442fc41c2b86b821562f.png",
            "link": "https://www.last.fm/music/rusha/_/kim%3F"
        },
        {
            "rank": "39",
            "title": "Малышка",
            "artist": "Sharlot",
            "playcount": 2,
            "image": "https://lastfm.freetls.fastly.net/i/u/300x300/2a96cbd8b46e442fc41c2b86b821562f.png",
            "link": "https://www.last.fm/music/Sharlot/_/%D0%9C%D0%B0%D0%BB%D1%8B%D1%88%D0%BA%D0%B0"
        },
        {
            "rank": "40",
            "title": "i wish i knew how to quit you",
            "artist": "sombr",
            "playcount": 2,
            "image": "https://lastfm.freetls.fastly.net/i/u/300x300/2a96cbd8b46e442fc41c2b86b821562f.png",
            "link": "https://www.last.fm/music/sombr/_/i+wish+i+knew+how+to+quit+you"
        },
        {
            "rank": "41",
            "title": "MUKANJYO",
            "artist": "Survive Said The Prophet",
            "playcount": 2,
            "image": "https://lastfm.freetls.fastly.net/i/u/300x300/2a96cbd8b46e442fc41c2b86b821562f.png",
            "link": "https://www.last.fm/music/Survive+Said+The+Prophet/_/MUKANJYO"
        },
        {
            "rank": "42",
            "title": "FE!N (feat. Playboi Carti)",
            "artist": "Travis Scott",
            "playcount": 2,
            "image": "https://lastfm.freetls.fastly.net/i/u/300x300/2a96cbd8b46e442fc41c2b86b821562f.png",
            "link": "https://www.last.fm/music/Travis+Scott/_/FE!N+(feat.+Playboi+Carti)"
        },
        {
            "rank": "43",
            "title": "Moonlight",
            "artist": "XXXTENTACION",
            "playcount": 2,
            "image": "https://lastfm.freetls.fastly.net/i/u/300x300/2a96cbd8b46e442fc41c2b86b821562f.png",
            "link": "https://www.last.fm/music/XXXTENTACION/_/Moonlight"
        },
        {
            "rank": "44",
            "title": "Sad!",
            "artist": "XXXTENTACION",
            "playcount": 2,
            "image": "https://lastfm.freetls.fastly.net/i/u/300x300/2a96cbd8b46e442fc41c2b86b821562f.png",
            "link": "https://www.last.fm/music/XXXTENTACION/_/Sad!"
        },
        {
            "rank": "45",
            "title": "You Say Run",
            "artist": "Yuki Hayashi",
            "playcount": 2,
            "image": "https://lastfm.freetls.fastly.net/i/u/300x300/2a96cbd8b46e442fc41c2b86b821562f.png",
            "link": "https://www.last.fm/music/Yuki+Hayashi/_/You+Say+Run"
        },
        {
            "rank": "46",
            "title": "REASON",
            "artist": "Yuzu",
            "playcount": 2,
            "image": "https://lastfm.freetls.fastly.net/i/u/300x300/2a96cbd8b46e442fc41c2b86b821562f.png",
            "link": "https://www.last.fm/music/+noredirect/Yuzu/_/REASON"
        },
        {
            "rank": "47",
            "title": "香車豪宅(Whips and Cribs)",
            "artist": "攬佬SKAI ISYOURGOD",
            "playcount": 2,
            "image": "https://lastfm.freetls.fastly.net/i/u/300x300/2a96cbd8b46e442fc41c2b86b821562f.png",
            "link": "https://www.last.fm/music/%E6%94%AC%E4%BD%ACSKAI+ISYOURGOD/_/%E9%A6%99%E8%BB%8A%E8%B1%AA%E5%AE%85(Whips+and+Cribs)"
        },
        {
            "rank": "48",
            "title": "BURN",
            "artist": "¥$",
            "playcount": 1,
            "image": "https://lastfm.freetls.fastly.net/i/u/300x300/2a96cbd8b46e442fc41c2b86b821562f.png",
            "link": "https://www.last.fm/music/%C2%A5$/_/BURN"
        },
        {
            "rank": "49",
            "title": "redrum",
            "artist": "21 Savage",
            "playcount": 1,
            "image": "https://lastfm.freetls.fastly.net/i/u/300x300/2a96cbd8b46e442fc41c2b86b821562f.png",
            "link": "https://www.last.fm/music/21+Savage/_/redrum"
        },
        {
            "rank": "50",
            "title": "No Limit",
            "artist": "999999999",
            "playcount": 1,
            "image": "https://lastfm.freetls.fastly.net/i/u/300x300/2a96cbd8b46e442fc41c2b86b821562f.png",
            "link": "https://www.last.fm/music/999999999/_/No+Limit"
        }
    ],
    "alltime": [
        {
            "rank": "1",
            "title": "Viva la Vida",
            "artist": "Coldplay",
            "playcount": 74,
            "image": "https://lastfm.freetls.fastly.net/i/u/300x300/2a96cbd8b46e442fc41c2b86b821562f.png",
            "link": "https://www.last.fm/music/Coldplay/_/Viva+la+Vida"
        },
        {
            "rank": "2",
            "title": "DIE TRYING",
            "artist": "PARTYNEXTDOOR",
            "playcount": 72,
            "image": "https://lastfm.freetls.fastly.net/i/u/300x300/2a96cbd8b46e442fc41c2b86b821562f.png",
            "link": "https://www.last.fm/music/PARTYNEXTDOOR/_/DIE+TRYING"
        },
        {
            "rank": "3",
            "title": "back to friends",
            "artist": "sombr",
            "playcount": 48,
            "image": "https://lastfm.freetls.fastly.net/i/u/300x300/2a96cbd8b46e442fc41c2b86b821562f.png",
            "link": "https://www.last.fm/music/sombr/_/back+to+friends"
        },
        {
            "rank": "4",
            "title": "we never dated",
            "artist": "sombr",
            "playcount": 34,
            "image": "https://lastfm.freetls.fastly.net/i/u/300x300/2a96cbd8b46e442fc41c2b86b821562f.png",
            "link": "https://www.last.fm/music/sombr/_/we+never+dated"
        },
        {
            "rank": "5",
            "title": "TUCA DONKA",
            "artist": "CURSEDEVIL",
            "playcount": 33,
            "image": "https://lastfm.freetls.fastly.net/i/u/300x300/2a96cbd8b46e442fc41c2b86b821562f.png",
            "link": "https://www.last.fm/music/CURSEDEVIL/_/TUCA+DONKA"
        },
        {
            "rank": "6",
            "title": "Bad Habit",
            "artist": "Steve Lacy",
            "playcount": 33,
            "image": "https://lastfm.freetls.fastly.net/i/u/300x300/2a96cbd8b46e442fc41c2b86b821562f.png",
            "link": "https://www.last.fm/music/Steve+Lacy/_/Bad+Habit"
        },
        {
            "rank": "7",
            "title": "ROXANNE",
            "artist": "Arizona Zervas",
            "playcount": 32,
            "image": "https://lastfm.freetls.fastly.net/i/u/300x300/2a96cbd8b46e442fc41c2b86b821562f.png",
            "link": "https://www.last.fm/music/Arizona+Zervas/_/ROXANNE"
        },
        {
            "rank": "8",
            "title": "Men Sen Siyaqty",
            "artist": "Darkhan Juzz",
            "playcount": 30,
            "image": "https://lastfm.freetls.fastly.net/i/u/300x300/2a96cbd8b46e442fc41c2b86b821562f.png",
            "link": "https://www.last.fm/music/Darkhan+Juzz/_/Men+Sen+Siyaqty"
        },
        {
            "rank": "9",
            "title": "Push Ups",
            "artist": "Drake",
            "playcount": 30,
            "image": "https://lastfm.freetls.fastly.net/i/u/300x300/2a96cbd8b46e442fc41c2b86b821562f.png",
            "link": "https://www.last.fm/music/Drake/_/Push+Ups"
        },
        {
            "rank": "10",
            "title": "kim?",
            "artist": "rusha",
            "playcount": 30,
            "image": "https://lastfm.freetls.fastly.net/i/u/300x300/2a96cbd8b46e442fc41c2b86b821562f.png",
            "link": "https://www.last.fm/music/rusha/_/kim%3F"
        },
        {
            "rank": "11",
            "title": "Малышка",
            "artist": "Sharlot",
            "playcount": 30,
            "image": "https://lastfm.freetls.fastly.net/i/u/300x300/2a96cbd8b46e442fc41c2b86b821562f.png",
            "link": "https://www.last.fm/music/Sharlot/_/%D0%9C%D0%B0%D0%BB%D1%8B%D1%88%D0%BA%D0%B0"
        },
        {
            "rank": "12",
            "title": "God's Plan",
            "artist": "Drake",
            "playcount": 29,
            "image": "https://lastfm.freetls.fastly.net/i/u/300x300/2a96cbd8b46e442fc41c2b86b821562f.png",
            "link": "https://www.last.fm/music/Drake/_/God%27s+Plan"
        },
        {
            "rank": "13",
            "title": "LOVE. FEAT. ZACARI.",
            "artist": "Kendrick Lamar",
            "playcount": 27,
            "image": "https://lastfm.freetls.fastly.net/i/u/300x300/2a96cbd8b46e442fc41c2b86b821562f.png",
            "link": "https://www.last.fm/music/Kendrick+Lamar/_/LOVE.+FEAT.+ZACARI."
        },
        {
            "rank": "14",
            "title": "恋風",
            "artist": "Lilas",
            "playcount": 27,
            "image": "https://lastfm.freetls.fastly.net/i/u/300x300/2a96cbd8b46e442fc41c2b86b821562f.png",
            "link": "https://www.last.fm/music/Lilas/_/%E6%81%8B%E9%A2%A8"
        },
        {
            "rank": "15",
            "title": "Daiynbyz ba?",
            "artist": "Alem",
            "playcount": 26,
            "image": "https://lastfm.freetls.fastly.net/i/u/300x300/2a96cbd8b46e442fc41c2b86b821562f.png",
            "link": "https://www.last.fm/music/Alem/_/Daiynbyz+ba%3F"
        },
        {
            "rank": "16",
            "title": "Kuiim",
            "artist": "Alem",
            "playcount": 26,
            "image": "https://lastfm.freetls.fastly.net/i/u/300x300/2a96cbd8b46e442fc41c2b86b821562f.png",
            "link": "https://www.last.fm/music/Alem/_/Kuiim"
        },
        {
            "rank": "17",
            "title": "i like the way you kiss me",
            "artist": "Artemas",
            "playcount": 25,
            "image": "https://lastfm.freetls.fastly.net/i/u/300x300/2a96cbd8b46e442fc41c2b86b821562f.png",
            "link": "https://www.last.fm/music/Artemas/_/i+like+the+way+you+kiss+me"
        },
        {
            "rank": "18",
            "title": "GIMME A HUG",
            "artist": "Drake",
            "playcount": 25,
            "image": "https://lastfm.freetls.fastly.net/i/u/300x300/2a96cbd8b46e442fc41c2b86b821562f.png",
            "link": "https://www.last.fm/music/Drake/_/GIMME+A+HUG"
        },
        {
            "rank": "19",
            "title": "夜に駆ける",
            "artist": "YOASOBI",
            "playcount": 24,
            "image": "https://lastfm.freetls.fastly.net/i/u/300x300/2a96cbd8b46e442fc41c2b86b821562f.png",
            "link": "https://www.last.fm/music/YOASOBI/_/%E5%A4%9C%E3%81%AB%E9%A7%86%E3%81%91%E3%82%8B"
        },
        {
            "rank": "20",
            "title": "Sheker",
            "artist": "Darkhan Juzz",
            "playcount": 23,
            "image": "https://lastfm.freetls.fastly.net/i/u/300x300/2a96cbd8b46e442fc41c2b86b821562f.png",
            "link": "https://www.last.fm/music/Darkhan+Juzz/_/Sheker"
        },
        {
            "rank": "21",
            "title": "Pain",
            "artist": "PinkPantheress",
            "playcount": 23,
            "image": "https://lastfm.freetls.fastly.net/i/u/300x300/2a96cbd8b46e442fc41c2b86b821562f.png",
            "link": "https://www.last.fm/music/PinkPantheress/_/Pain"
        },
        {
            "rank": "22",
            "title": "NOKIA",
            "artist": "Drake",
            "playcount": 22,
            "image": "https://lastfm.freetls.fastly.net/i/u/300x300/2a96cbd8b46e442fc41c2b86b821562f.png",
            "link": "https://www.last.fm/music/Drake/_/NOKIA"
        },
        {
            "rank": "23",
            "title": "12 to 12",
            "artist": "sombr",
            "playcount": 22,
            "image": "https://lastfm.freetls.fastly.net/i/u/300x300/2a96cbd8b46e442fc41c2b86b821562f.png",
            "link": "https://www.last.fm/music/sombr/_/12+to+12"
        },
        {
            "rank": "24",
            "title": "SPIT IN MY FACE!",
            "artist": "ThxSoMch",
            "playcount": 22,
            "image": "https://lastfm.freetls.fastly.net/i/u/300x300/2a96cbd8b46e442fc41c2b86b821562f.png",
            "link": "https://www.last.fm/music/ThxSoMch/_/SPIT+IN+MY+FACE!"
        },
        {
            "rank": "25",
            "title": "ダブルシャッフル",
            "artist": "Nana Mizuki",
            "playcount": 21,
            "image": "https://lastfm.freetls.fastly.net/i/u/300x300/2a96cbd8b46e442fc41c2b86b821562f.png",
            "link": "https://www.last.fm/music/Nana+Mizuki/_/%E3%83%80%E3%83%96%E3%83%AB%E3%82%B7%E3%83%A3%E3%83%83%E3%83%95%E3%83%AB"
        },
        {
            "rank": "26",
            "title": "Look at Me!",
            "artist": "XXXTENTACION",
            "playcount": 21,
            "image": "https://lastfm.freetls.fastly.net/i/u/300x300/2a96cbd8b46e442fc41c2b86b821562f.png",
            "link": "https://www.last.fm/music/XXXTENTACION/_/Look+at+Me!"
        },
        {
            "rank": "27",
            "title": "Sad!",
            "artist": "XXXTENTACION",
            "playcount": 21,
            "image": "https://lastfm.freetls.fastly.net/i/u/300x300/2a96cbd8b46e442fc41c2b86b821562f.png",
            "link": "https://www.last.fm/music/XXXTENTACION/_/Sad!"
        },
        {
            "rank": "28",
            "title": "Shyraq",
            "artist": "Darkhan Juzz",
            "playcount": 20,
            "image": "https://lastfm.freetls.fastly.net/i/u/300x300/2a96cbd8b46e442fc41c2b86b821562f.png",
            "link": "https://www.last.fm/music/Darkhan+Juzz/_/Shyraq"
        },
        {
            "rank": "29",
            "title": "Family Matters",
            "artist": "Drake",
            "playcount": 20,
            "image": "https://lastfm.freetls.fastly.net/i/u/300x300/2a96cbd8b46e442fc41c2b86b821562f.png",
            "link": "https://www.last.fm/music/Drake/_/Family+Matters"
        },
        {
            "rank": "30",
            "title": "What Did I Miss?",
            "artist": "Drake",
            "playcount": 20,
            "image": "https://lastfm.freetls.fastly.net/i/u/300x300/2a96cbd8b46e442fc41c2b86b821562f.png",
            "link": "https://www.last.fm/music/Drake/_/What+Did+I+Miss%3F"
        },
        {
            "rank": "31",
            "title": "DNA.",
            "artist": "Kendrick Lamar",
            "playcount": 20,
            "image": "https://lastfm.freetls.fastly.net/i/u/300x300/2a96cbd8b46e442fc41c2b86b821562f.png",
            "link": "https://www.last.fm/music/Kendrick+Lamar/_/DNA."
        },
        {
            "rank": "32",
            "title": "euphoria",
            "artist": "Kendrick Lamar",
            "playcount": 20,
            "image": "https://lastfm.freetls.fastly.net/i/u/300x300/2a96cbd8b46e442fc41c2b86b821562f.png",
            "link": "https://www.last.fm/music/Kendrick+Lamar/_/euphoria"
        },
        {
            "rank": "33",
            "title": "luther (with SZA)",
            "artist": "Kendrick Lamar",
            "playcount": 20,
            "image": "https://lastfm.freetls.fastly.net/i/u/300x300/2a96cbd8b46e442fc41c2b86b821562f.png",
            "link": "https://www.last.fm/music/Kendrick+Lamar/_/luther+(with+SZA)"
        },
        {
            "rank": "34",
            "title": "Judas",
            "artist": "Lady Gaga",
            "playcount": 20,
            "image": "https://lastfm.freetls.fastly.net/i/u/300x300/2a96cbd8b46e442fc41c2b86b821562f.png",
            "link": "https://www.last.fm/music/Lady+Gaga/_/Judas"
        },
        {
            "rank": "35",
            "title": "Jerk",
            "artist": "Oliver Tree",
            "playcount": 20,
            "image": "https://lastfm.freetls.fastly.net/i/u/300x300/2a96cbd8b46e442fc41c2b86b821562f.png",
            "link": "https://www.last.fm/music/Oliver+Tree/_/Jerk"
        },
        {
            "rank": "36",
            "title": "Снова я напиваюсь",
            "artist": "SLAVA MARLOW",
            "playcount": 20,
            "image": "https://lastfm.freetls.fastly.net/i/u/300x300/2a96cbd8b46e442fc41c2b86b821562f.png",
            "link": "https://www.last.fm/music/SLAVA+MARLOW/_/%D0%A1%D0%BD%D0%BE%D0%B2%D0%B0+%D1%8F+%D0%BD%D0%B0%D0%BF%D0%B8%D0%B2%D0%B0%D1%8E%D1%81%D1%8C"
        },
        {
            "rank": "37",
            "title": "青のすみか",
            "artist": "Tatsuya Kitani",
            "playcount": 20,
            "image": "https://lastfm.freetls.fastly.net/i/u/300x300/2a96cbd8b46e442fc41c2b86b821562f.png",
            "link": "https://www.last.fm/music/Tatsuya+Kitani/_/%E9%9D%92%E3%81%AE%E3%81%99%E3%81%BF%E3%81%8B"
        },
        {
            "rank": "38",
            "title": "Moonlight",
            "artist": "XXXTENTACION",
            "playcount": 20,
            "image": "https://lastfm.freetls.fastly.net/i/u/300x300/2a96cbd8b46e442fc41c2b86b821562f.png",
            "link": "https://www.last.fm/music/XXXTENTACION/_/Moonlight"
        },
        {
            "rank": "39",
            "title": "CARNIVAL",
            "artist": "¥$",
            "playcount": 19,
            "image": "https://lastfm.freetls.fastly.net/i/u/300x300/2a96cbd8b46e442fc41c2b86b821562f.png",
            "link": "https://www.last.fm/music/%C2%A5$/_/CARNIVAL"
        },
        {
            "rank": "40",
            "title": "オトノケ - Otonoke",
            "artist": "Creepy Nuts",
            "playcount": 19,
            "image": "https://lastfm.freetls.fastly.net/i/u/300x300/2a96cbd8b46e442fc41c2b86b821562f.png",
            "link": "https://www.last.fm/music/Creepy+Nuts/_/%E3%82%AA%E3%83%88%E3%83%8E%E3%82%B1+-+Otonoke"
        },
        {
            "rank": "41",
            "title": "Ol",
            "artist": "Darkhan Juzz",
            "playcount": 19,
            "image": "https://lastfm.freetls.fastly.net/i/u/300x300/2a96cbd8b46e442fc41c2b86b821562f.png",
            "link": "https://www.last.fm/music/Darkhan+Juzz/_/Ol"
        },
        {
            "rank": "42",
            "title": "Qubylmaly",
            "artist": "Darkhan Juzz",
            "playcount": 19,
            "image": "https://lastfm.freetls.fastly.net/i/u/300x300/2a96cbd8b46e442fc41c2b86b821562f.png",
            "link": "https://www.last.fm/music/Darkhan+Juzz/_/Qubylmaly"
        },
        {
            "rank": "43",
            "title": "Úıde",
            "artist": "Darkhan Juzz",
            "playcount": 19,
            "image": "https://lastfm.freetls.fastly.net/i/u/300x300/2a96cbd8b46e442fc41c2b86b821562f.png",
            "link": "https://www.last.fm/music/Darkhan+Juzz/_/%C3%9A%C4%B1de"
        },
        {
            "rank": "44",
            "title": "TORE UP",
            "artist": "Don Toliver",
            "playcount": 19,
            "image": "https://lastfm.freetls.fastly.net/i/u/300x300/2a96cbd8b46e442fc41c2b86b821562f.png",
            "link": "https://www.last.fm/music/Don+Toliver/_/TORE+UP"
        },
        {
            "rank": "45",
            "title": "Usta",
            "artist": "rusha",
            "playcount": 19,
            "image": "https://lastfm.freetls.fastly.net/i/u/300x300/2a96cbd8b46e442fc41c2b86b821562f.png",
            "link": "https://www.last.fm/music/rusha/_/Usta"
        },
        {
            "rank": "46",
            "title": "undressed",
            "artist": "sombr",
            "playcount": 19,
            "image": "https://lastfm.freetls.fastly.net/i/u/300x300/2a96cbd8b46e442fc41c2b86b821562f.png",
            "link": "https://www.last.fm/music/sombr/_/undressed"
        },
        {
            "rank": "47",
            "title": "the perfect pair",
            "artist": "beabadoobee",
            "playcount": 18,
            "image": "https://lastfm.freetls.fastly.net/i/u/300x300/2a96cbd8b46e442fc41c2b86b821562f.png",
            "link": "https://www.last.fm/music/beabadoobee/_/the+perfect+pair"
        },
        {
            "rank": "48",
            "title": "Esindi Ji",
            "artist": "Darkhan Juzz",
            "playcount": 18,
            "image": "https://lastfm.freetls.fastly.net/i/u/300x300/2a96cbd8b46e442fc41c2b86b821562f.png",
            "link": "https://www.last.fm/music/Darkhan+Juzz/_/Esindi+Ji"
        },
        {
            "rank": "49",
            "title": "ウィーアー!",
            "artist": "Hiroshi Kitadani",
            "playcount": 18,
            "image": "https://lastfm.freetls.fastly.net/i/u/300x300/2a96cbd8b46e442fc41c2b86b821562f.png",
            "link": "https://www.last.fm/music/Hiroshi+Kitadani/_/%E3%82%A6%E3%82%A3%E3%83%BC%E3%82%A2%E3%83%BC!"
        },
        {
            "rank": "50",
            "title": "Life Goes On",
            "artist": "Oliver Tree",
            "playcount": 18,
            "image": "https://lastfm.freetls.fastly.net/i/u/300x300/2a96cbd8b46e442fc41c2b86b821562f.png",
            "link": "https://www.last.fm/music/Oliver+Tree/_/Life+Goes+On"
        }
    ],
    "last_updated": 1784038850
}